<?xml version="1.0" encoding="utf-8"?>
<Entity parent="brit|sword_long|inf_charge|template_unit_champion_infantry_swordsman">
  <Identity>
    <Civ>brit</Civ>
    <GenericName>Brythonic Champion Bezerk mode</GenericName>
    <SpecificName>Argos ríastrad </SpecificName>
    <Tooltip>Swing 2 swords; 50% more dmg, 1 tenth of a second faster repeat time. Add 75 HP but -1 HP every 2 seconds in Bezerk Mode. +25% faster walk speed and 50% faser acceleartion but no armor.</Tooltip>
    <Icon>units/brit/champ_berserk.png</Icon>
  </Identity>
  <Attack>
    <Melee>
      <AttackName context="Name of an attack using a double-edged sword.">Sword</AttackName>
      <Damage>
        <Hack op="mul">1.5</Hack>
	      <Pierce op="mul">1.5</Pierce>
      </Damage>
       <RepeatTime op="add">-100</RepeatTime>
    </Melee>
  </Attack>
 <Health>
    <Max op="add">75</Max>
    <RegenRate>-0.5</RegenRate>
    <Unhealable>true</Unhealable>
  </Health>
  <Upgrade>
    <Berserker_Rage>
      <Entity>units/brit/champion_infantry_swordsman</Entity>
      <Tooltip>Put on your armour again.</Tooltip>
      <Variant>upgrading</Variant>
      <Time>6</Time>
    </Berserker_Rage>
  </Upgrade>
<UnitMotion>
    <WalkSpeed op="mul">1.25</WalkSpeed>
    <Acceleration op="mul">1.5</Acceleration>
  </UnitMotion>
  <VisualActor>
    <Actor>units/britons/infantry_swordsman_berserk.xml</Actor>
  </VisualActor>
</Entity>
